pyrocore/__init__.py
pyrocore/config.py
pyrocore/error.py
pyrocore/daemon/__init__.py
pyrocore/daemon/webapp.py
pyrocore/data/config/bash-completion
pyrocore/data/config/config.ini
pyrocore/data/config/config.py
pyrocore/data/config/logging.cron.ini
pyrocore/data/config/logging.scripts.ini
pyrocore/data/config/logging.torque.ini
pyrocore/data/config/rtorrent-pyro.rc
pyrocore/data/config/torque.ini
pyrocore/data/config/color-schemes/default-16.rc
pyrocore/data/config/color-schemes/default-256.rc
pyrocore/data/config/color-schemes/default-8.rc
pyrocore/data/config/color-schemes/happy-pastel.rc
pyrocore/data/config/color-schemes/solarized-blue.rc
pyrocore/data/config/color-schemes/solarized-yellow.rc
pyrocore/data/config/rtorrent.d/00-default.rc
pyrocore/data/config/rtorrent.d/auto-scrape.rc
pyrocore/data/config/rtorrent.d/bind-navigation-keys.rc
pyrocore/data/config/rtorrent.d/categories.rc
pyrocore/data/config/rtorrent.d/collapse-built-in-views.rc
pyrocore/data/config/rtorrent.d/commands.rc
pyrocore/data/config/rtorrent.d/helper-methods.rc
pyrocore/data/config/rtorrent.d/logging.rc
pyrocore/data/config/rtorrent.d/quick-help.rc
pyrocore/data/config/rtorrent.d/theming.rc
pyrocore/data/config/rtorrent.d/timestamps.rc
pyrocore/data/config/rtorrent.d/torque.rc
pyrocore/data/config/rtorrent.d/view-indemand.rc
pyrocore/data/config/rtorrent.d/view-messages.rc
pyrocore/data/config/rtorrent.d/view-tagged.rc
pyrocore/data/config/rtorrent.d/view-trackers.rc
pyrocore/data/config/templates/irc_status.txt
pyrocore/data/config/templates/json
pyrocore/data/config/templates/orphans.txt
pyrocore/data/config/templates/rtorstat.html
pyrocore/data/config/templates/conky/conkyrc
pyrocore/data/config/templates/conky/rtorstat.txt
pyrocore/data/htdocs/favicon.ico
pyrocore/data/htdocs/index.html
pyrocore/data/htdocs/css/custom.css
pyrocore/data/htdocs/css/style.css
pyrocore/data/htdocs/img/pyroscope.png
pyrocore/data/htdocs/js/charts.js
pyrocore-0.5.3.data/data/EGG-INFO/LICENSE
pyrocore-0.5.3.data/data/EGG-INFO/README.md
pyrocore-0.5.3.data/data/EGG-INFO/changelog
pyrocore-0.5.3.dist-info/DESCRIPTION.rst
pyrocore-0.5.3.dist-info/METADATA
pyrocore-0.5.3.dist-info/RECORD
pyrocore-0.5.3.dist-info/WHEEL
pyrocore-0.5.3.dist-info/entry_points.txt
pyrocore-0.5.3.dist-info/metadata.json
pyrocore-0.5.3.dist-info/top_level.txt
