Metadata-Version: 2.0
Name: pyrocore
Version: 0.5.3
Summary: PyroCore - Python Torrent Tools Core Package
Home-page: https://github.com/pyroscope/pyrocore
Author: The PyroScope Project
Author-email: pyroscope.project@gmail.com
License: Copyright (c) 2009 - 2017 The PyroScope Project <pyroscope.project@gmail.com>
Keywords: bittorrent rtorrent cli python
Platform: UNKNOWN
Classifier: Development Status :: 5 - Production/Stable
Classifier: Environment :: Console
Classifier: Intended Audience :: End Users/Desktop
Classifier: Intended Audience :: Developers
Classifier: License :: OSI Approved :: GNU General Public License (GPL)
Classifier: Natural Language :: English
Classifier: Operating System :: POSIX
Classifier: Programming Language :: Python :: 2.7
Classifier: Topic :: Communications :: File Sharing
Classifier: Topic :: Software Development :: Libraries :: Python Modules
Classifier: Topic :: Utilities
Requires-Dist: ProxyTypes (>=0.9)
Requires-Dist: pyrobase (>=0.2)
Provides-Extra: FlexGet
Requires-Dist: flexget (>=1.0); extra == 'FlexGet'
Provides-Extra: pyrotorque
Requires-Dist: APScheduler (<3,>=2.0.2); extra == 'pyrotorque'
Provides-Extra: pyrotorque.httpd
Requires-Dist: WebOb (>=1.2.3); extra == 'pyrotorque.httpd'
Requires-Dist: psutil (>=0.6.1); extra == 'pyrotorque.httpd'
Requires-Dist: waitress (>=0.8.2); extra == 'pyrotorque.httpd'
Provides-Extra: templating
Requires-Dist: Tempita (>=0.5.1); extra == 'templating'
